{"frames":{"planet1":{"frame":{"x":87,"y":0,"w":86,"h":86},"rotated":false,"trimmed":false,"spriteSourceSize":{"x":0,"y":0,"w":86,"h":86},"sourceSize":{"w":86,"h":86}},"planet2":{"frame":{"x":174,"y":0,"w":86,"h":86},"rotated":false,"trimmed":false,"spriteSourceSize":{"x":0,"y":0,"w":86,"h":86},"sourceSize":{"w":86,"h":86}},"planet3":{"frame":{"x":174,"y":174,"w":86,"h":86},"rotated":false,"trimmed":false,"spriteSourceSize":{"x":0,"y":0,"w":86,"h":86},"sourceSize":{"w":86,"h":86}},"planet4":{"frame":{"x":174,"y":87,"w":86,"h":86},"rotated":false,"trimmed":false,"spriteSourceSize":{"x":0,"y":0,"w":86,"h":86},"sourceSize":{"w":86,"h":86}},"planet5":{"frame":{"x":0,"y":174,"w":137,"h":86},"rotated":false,"trimmed":false,"spriteSourceSize":{"x":0,"y":0,"w":137,"h":86},"sourceSize":{"w":137,"h":86}},"planet6":{"frame":{"x":0,"y":87,"w":86,"h":86},"rotated":false,"trimmed":false,"spriteSourceSize":{"x":0,"y":0,"w":86,"h":86},"sourceSize":{"w":86,"h":86}},"planet7":{"frame":{"x":87,"y":87,"w":86,"h":86},"rotated":false,"trimmed":false,"spriteSourceSize":{"x":0,"y":0,"w":86,"h":86},"sourceSize":{"w":86,"h":86}},"planet8":{"frame":{"x":0,"y":0,"w":86,"h":86},"rotated":false,"trimmed":false,"spriteSourceSize":{"x":0,"y":0,"w":86,"h":86},"sourceSize":{"w":86,"h":86}}},"meta":{"app":"https://www.leshylabs.com/apps/sstool/","version":"Leshy SpriteSheet Tool v0.8.4","image":"planets.png","size":{"w":260,"h":260},"scale":1}}